Metadata-Version: 2.1
Name: ascgraph
Version: 1.3
Summary: Ascii graphics in console
Home-page: UNKNOWN
Author-email: farmbsbraw@gmail.com
License: UNKNOWN
Platform: UNKNOWN
